ltp/__init__.py
mmtests/__init__.py
tradefed/__init__.py
tradefed/tasks.py
squad_linaro_plugins-1.35.2.dist-info/COPYING
squad_linaro_plugins-1.35.2.dist-info/METADATA
squad_linaro_plugins-1.35.2.dist-info/WHEEL
squad_linaro_plugins-1.35.2.dist-info/entry_points.txt
squad_linaro_plugins-1.35.2.dist-info/top_level.txt
squad_linaro_plugins-1.35.2.dist-info/RECORD
