Metadata-Version: 2.2
Name: squad-linaro-plugins
Version: 1.35.2
Summary: SQUAD plugins collection
Home-page: https://github.com/linaro/squadplugins
Author: Charles Oliveira
Author-email: charles.oliveira@linaro.org
License: AGPLv3+
Platform: any
License-File: COPYING
Requires-Dist: squad[postgres]>=1.81
Requires-Dist: requests
Dynamic: author
Dynamic: author-email
Dynamic: description
Dynamic: home-page
Dynamic: license
Dynamic: platform
Dynamic: requires-dist
Dynamic: summary
